filoma/__init__.py
filoma/_version.py
filoma/cli.py
filoma/core/__init__.py
filoma/core/command_runner.py
filoma/core/fd_integration.py
filoma/dataframe.py
filoma/dedup.py
filoma/directories/__init__.py
filoma/directories/directory_profiler.py
filoma/directories/fd_finder.py
filoma/files/__init__.py
filoma/files/file_profiler.py
filoma/filoma_core.cpython-311-darwin.so
filoma/images/__init__.py
filoma/images/base.py
filoma/images/image_profiler.py
filoma/images/npy_profiler.py
filoma/images/png_profiler.py
filoma/images/tif_profiler.py
filoma/images/zarr_profiler.py
filoma-1.11.1.dist-info/METADATA
filoma-1.11.1.dist-info/WHEEL
filoma-1.11.1.dist-info/entry_points.txt
filoma-1.11.1.dist-info/licenses/LICENSE.txt
filoma-1.11.1.dist-info/RECORD
