Metadata-Version: 2.4
Name: filoma
Version: 1.11.1
Requires-Dist: rich>=13.0.0
Requires-Dist: numpy>=1.26.0
Requires-Dist: pillow>=10.0.0
Requires-Dist: polars>=1.0.0
Requires-Dist: loguru>=0.7.0
Requires-Dist: ipython>=9.4.0
Requires-Dist: typer>=0.12.0
Requires-Dist: questionary>=2.0.0
Requires-Dist: datasketch>=1.5.3 ; extra == 'dedup'
Requires-Dist: pillow>=10.0.0 ; extra == 'dedup'
Requires-Dist: pytest>=8.3.5 ; extra == 'dev'
Requires-Dist: pytest-xdist>=3.2.0 ; extra == 'dev'
Requires-Dist: ruff>=0.1.0 ; extra == 'dev'
Requires-Dist: pre-commit>=4.2.0 ; extra == 'dev'
Requires-Dist: maturin>=1.9.0 ; extra == 'dev'
Requires-Dist: twine>=6.1.0 ; extra == 'dev'
Requires-Dist: ipython>=9.4.0 ; extra == 'dev'
Requires-Dist: ipykernel>=6.30.1 ; extra == 'dev'
Requires-Dist: loguru>=0.7.0 ; extra == 'docs'
Requires-Dist: mkdocs>=1.5.0 ; extra == 'docs'
Requires-Dist: mkdocs-material>=9.0.0 ; extra == 'docs'
Requires-Dist: mkdocstrings>=0.23.0 ; extra == 'docs'
Requires-Dist: mkdocstrings-python>=0.23.0 ; extra == 'docs'
Requires-Dist: pymdown-extensions ; extra == 'docs'
Requires-Dist: nbconvert>=7.5.0 ; extra == 'docs'
Requires-Dist: ipykernel>=6.30.1 ; extra == 'docs'
Requires-Dist: ipython>=9.4.0 ; extra == 'docs'
Requires-Dist: nbformat>=5.7.0 ; extra == 'docs'
Requires-Dist: jupyterlab>=4.0.0 ; extra == 'docs'
Requires-Dist: pyarrow>=12.0.0 ; extra == 'docs'
Requires-Dist: pandas>=2.0.0 ; extra == 'pd'
Requires-Dist: pyarrow>=12.0.0 ; extra == 'pd'
Requires-Dist: ipython>=9.4.0 ; extra == 'pd'
Requires-Dist: ipykernel>=6.30.1 ; extra == 'pd'
Requires-Dist: jupyterlab>=4.0.0 ; extra == 'pd'
Provides-Extra: dedup
Provides-Extra: dev
Provides-Extra: docs
Provides-Extra: pd
License-File: LICENSE.txt
Summary: Modular Python tool for profiling files, analyzing directory structures, and inspecting image data
Requires-Python: >=3.11, <3.15
